Metadata-Version: 2.1
Name: FlowCytometryTools
Version: 0.5.1
Summary: A python package for performing flow cytometry analysis
Home-page: http://eyurtsev.github.io/FlowCytometryTools/
Author: Jonathan Friedman, Eugene Yurtsev
Author-email: eyurtsev@gmail.com
License: MIT
Download-URL: https://github.com/eyurtsev/FlowCytometryTools/archive/v0.5.1.zip
Keywords: flow cytometry,data analysis,cytometry,single cell
Platform: UNKNOWN
Classifier: Intended Audience :: Science/Research
Classifier: Programming Language :: Python :: 2.7
Classifier: Topic :: Scientific/Engineering :: Bio-Informatics
Classifier: Topic :: Scientific/Engineering :: Medical Science Apps.
Requires-Dist: setuptools
Requires-Dist: decorator
Requires-Dist: fcsparser (>=0.1.1)
